zscTest/__init__.py
zscTest/add_num.py
zscTest-1.0.0.dist-info/METADATA
zscTest-1.0.0.dist-info/WHEEL
zscTest-1.0.0.dist-info/license.txt
zscTest-1.0.0.dist-info/top_level.txt
zscTest-1.0.0.dist-info/RECORD
