Metadata-Version: 2.1
Name: zscTest
Version: 1.0.0
Summary: the utils
Author: zhengshuchan
Author-email: 749887528@qq.com
License: Copyright (c) 2023 zhengshuchan
Requires-Python: >=3.7
License-File: license.txt
